TCPlog/__init__.py
TCPlog/__main__.py
TCPlog/broadcast_log_server.py
TCPlog/flow.py
TCPlog/sample.py
TCPlog/tcplog.py
TCPplot/__init__.py
TCPplot/__main__.py
TCPplot/tcpplot.py
tcplog/__init__.py
tcplog/__main__.py
tcplog/flow.py
tcplog/flows.py
tcplog/info_registry.py
tcplog/main.py
tcplog/sample.py
tcplog/tcplog.py
tcplog/backends/__init__.py
tcplog/backends/backend_base.py
tcplog/backends/gui/__init__.py
tcplog/backends/gui/curses.py
tcplog/backends/gui/gui_base.py
tcplog/backends/gui/progress.py
tcplog/backends/input/__init__.py
tcplog/backends/input/file.py
tcplog/backends/input/input_base.py
tcplog/backends/input/tcpinfo.py
tcplog/backends/input/tcpprobe.py
tcplog/backends/output/__init__.py
tcplog/backends/output/file.py
tcplog/backends/output/output_base.py
tcplog/backends/output/socket.py
tcplog/backends/output/socket_broadcast_log_server.py
tcplog/backends/output/stdout.py
tcplog/utils/__init__.py
tcplog/utils/utilty.py
tcplog-0.2.10.dist-info/AUTHORS.txt
tcplog-0.2.10.dist-info/LICENSE.txt
tcplog-0.2.10.dist-info/METADATA
tcplog-0.2.10.dist-info/WHEEL
tcplog-0.2.10.dist-info/entry_points.txt
tcplog-0.2.10.dist-info/top_level.txt
tcplog-0.2.10.dist-info/RECORD
