Metadata-Version: 2.1
Name: tcplog
Version: 0.2.10
Summary: Tool to log and analyze TCP flows.
Home-page: https://git.scc.kit.edu/CPUnetLOG/TCPlog/
Author: Karlsruhe Institute of Technology - Institute of Telematics
Author-email: telematics@tm.kit.edu
Maintainer: Michael Koenig
Maintainer-email: michael.koenig2@student.kit.edu
License: BSD
Keywords: tcp,flow,log,analyze,network,traffic
Platform: Linux
Classifier: Development Status :: 4 - Beta
Classifier: License :: OSI Approved :: BSD License
Classifier: Programming Language :: Python :: 3
Classifier: Programming Language :: Python :: 3.5
Classifier: Operating System :: POSIX :: Linux
Classifier: Environment :: Console
Classifier: Environment :: Console :: Curses
Classifier: Natural Language :: English
Classifier: Intended Audience :: Education
Classifier: Intended Audience :: Information Technology
Classifier: Intended Audience :: Science/Research
Classifier: Intended Audience :: System Administrators
Classifier: Intended Audience :: Telecommunications Industry
Classifier: Topic :: Scientific/Engineering
Classifier: Topic :: Internet
Classifier: Topic :: System :: Logging
Classifier: Topic :: System :: Networking
Classifier: Topic :: System :: Networking :: Monitoring
Classifier: Topic :: System :: Operating System Kernels :: Linux
Classifier: Topic :: Utilities
Requires-Dist: tcpinfo (>=0.2.1)
Provides-Extra: live_visualization
Requires-Dist: tcpliveplot (>=0.2); extra == 'live_visualization'
